[
  {
    "description": "    Sendo eu um usuário já cadastrado por um administrador,\n    espero conseguir acessar o sistema.",
    "keyword": "Funcionalidade",
    "name": "Login",
    "line": 3,
    "id": "login",
    "tags": [],
    "uri": "src\\features\\login.feature",
    "elements": [
      {
        "id": "login;login-com-sucesso",
        "keyword": "Scenario",
        "line": 18,
        "name": "Login com sucesso",
        "tags": [],
        "type": "scenario",
        "steps": [
          {
            "arguments": [],
            "keyword": "Dado ",
            "line": 8,
            "name": "que eu navego até o site \"http://localhost/\"",
            "match": {
              "location": "src\\specs\\login.spec.js:27"
            },
            "result": {
              "status": "passed",
              "duration": 6419000000
            }
          },
          {
            "arguments": [],
            "keyword": "Quando ",
            "line": 9,
            "name": "eu entro com meu cpf \"111.111.111-11\"",
            "match": {
              "location": "src\\specs\\login.spec.js:37"
            },
            "result": {
              "status": "passed",
              "duration": 323000000
            }
          },
          {
            "arguments": [],
            "keyword": "E ",
            "line": 10,
            "name": "eu entro com minha senha \"12345678\"",
            "match": {
              "location": "src\\specs\\login.spec.js:41"
            },
            "result": {
              "status": "passed",
              "duration": 350000000
            }
          },
          {
            "arguments": [],
            "keyword": "E ",
            "line": 11,
            "name": "seleciono a primeira opção de unidade",
            "match": {
              "location": "src\\specs\\login.spec.js:45"
            },
            "result": {
              "status": "passed",
              "duration": 1198000000
            }
          },
          {
            "arguments": [],
            "keyword": "Então ",
            "line": 12,
            "name": "eu clico para entrar",
            "match": {
              "location": "src\\specs\\login.spec.js:49"
            },
            "result": {
              "status": "passed",
              "duration": 978000000
            }
          },
          {
            "arguments": [],
            "keyword": "E ",
            "line": 13,
            "name": "meu nome \"Usuário 1\" deve estar visível na página inicial",
            "match": {
              "location": "src\\specs\\login.spec.js:54"
            },
            "result": {
              "status": "passed",
              "duration": 170000000
            }
          },
          {
            "arguments": [],
            "keyword": "E ",
            "line": 14,
            "name": "eu faço Logoff",
            "match": {
              "location": "src\\specs\\login.spec.js:58"
            },
            "result": {
              "status": "passed",
              "duration": 481000000
            }
          },
          {
            "keyword": "After",
            "hidden": true,
            "match": {
              "location": "node_modules\\protractor-cucumber-framework\\lib\\resultsCapturer.js:27"
            },
            "result": {
              "status": "passed",
              "duration": 1000000
            }
          }
        ]
      },
      {
        "id": "login;login-com-sucesso",
        "keyword": "Scenario",
        "line": 19,
        "name": "Login com sucesso",
        "tags": [],
        "type": "scenario",
        "steps": [
          {
            "arguments": [],
            "keyword": "Dado ",
            "line": 8,
            "name": "que eu navego até o site \"http://localhost/\"",
            "match": {
              "location": "src\\specs\\login.spec.js:27"
            },
            "result": {
              "status": "passed",
              "duration": 2655000000
            }
          },
          {
            "arguments": [],
            "keyword": "Quando ",
            "line": 9,
            "name": "eu entro com meu cpf \"222.222.222-22\"",
            "match": {
              "location": "src\\specs\\login.spec.js:37"
            },
            "result": {
              "status": "passed",
              "duration": 307000000
            }
          },
          {
            "arguments": [],
            "keyword": "E ",
            "line": 10,
            "name": "eu entro com minha senha \"12345678\"",
            "match": {
              "location": "src\\specs\\login.spec.js:41"
            },
            "result": {
              "status": "passed",
              "duration": 286000000
            }
          },
          {
            "arguments": [],
            "keyword": "E ",
            "line": 11,
            "name": "seleciono a primeira opção de unidade",
            "match": {
              "location": "src\\specs\\login.spec.js:45"
            },
            "result": {
              "status": "passed",
              "duration": 743000000
            }
          },
          {
            "arguments": [],
            "keyword": "Então ",
            "line": 12,
            "name": "eu clico para entrar",
            "match": {
              "location": "src\\specs\\login.spec.js:49"
            },
            "result": {
              "status": "passed",
              "duration": 773000000
            }
          },
          {
            "arguments": [],
            "keyword": "E ",
            "line": 13,
            "name": "meu nome \"Usuário 2\" deve estar visível na página inicial",
            "match": {
              "location": "src\\specs\\login.spec.js:54"
            },
            "result": {
              "status": "passed",
              "duration": 162000000
            }
          },
          {
            "arguments": [],
            "keyword": "E ",
            "line": 14,
            "name": "eu faço Logoff",
            "match": {
              "location": "src\\specs\\login.spec.js:58"
            },
            "result": {
              "status": "passed",
              "duration": 446000000
            }
          },
          {
            "keyword": "After",
            "hidden": true,
            "match": {
              "location": "node_modules\\protractor-cucumber-framework\\lib\\resultsCapturer.js:27"
            },
            "result": {
              "status": "passed",
              "duration": 1000000
            }
          }
        ]
      },
      {
        "id": "login;login-com-sucesso-gravado-pelo-blazemeter",
        "keyword": "Scenario",
        "line": 21,
        "name": "Login com sucesso Gravado pelo BlazeMeter",
        "tags": [],
        "type": "scenario",
        "steps": [
          {
            "arguments": [],
            "keyword": "Dado ",
            "line": 22,
            "name": "que eu desejo obter um script de carga para a funcionalidade \"login\"",
            "match": {
              "location": "src\\specs\\login.spec.js:20"
            },
            "result": {
              "status": "passed",
              "duration": 1000000
            }
          },
          {
            "arguments": [],
            "keyword": "Então ",
            "line": 23,
            "name": "eu inicio uma gravação do BlazeMeter",
            "match": {
              "location": "src\\specs\\login.spec.js:64"
            },
            "result": {
              "status": "passed",
              "duration": 23778000000
            }
          },
          {
            "arguments": [],
            "keyword": "Dado ",
            "line": 24,
            "name": "que eu navego até o site \"http://localhost/\"",
            "match": {
              "location": "src\\specs\\login.spec.js:27"
            },
            "result": {
              "status": "passed",
              "duration": 3552000000
            }
          },
          {
            "arguments": [],
            "keyword": "Quando ",
            "line": 25,
            "name": "eu entro com meu cpf \"111.111.111-11\"",
            "match": {
              "location": "src\\specs\\login.spec.js:37"
            },
            "result": {
              "status": "passed",
              "duration": 266000000
            }
          },
          {
            "arguments": [],
            "keyword": "E ",
            "line": 26,
            "name": "eu entro com minha senha \"12345678\"",
            "match": {
              "location": "src\\specs\\login.spec.js:41"
            },
            "result": {
              "status": "passed",
              "duration": 255000000
            }
          },
          {
            "arguments": [],
            "keyword": "E ",
            "line": 27,
            "name": "seleciono a primeira opção de unidade",
            "match": {
              "location": "src\\specs\\login.spec.js:45"
            },
            "result": {
              "status": "passed",
              "duration": 1221000000
            }
          },
          {
            "arguments": [],
            "keyword": "Então ",
            "line": 28,
            "name": "eu clico para entrar",
            "match": {
              "location": "src\\specs\\login.spec.js:49"
            },
            "result": {
              "status": "passed",
              "duration": 1106000000
            }
          },
          {
            "arguments": [],
            "keyword": "E ",
            "line": 29,
            "name": "meu nome \"Usuário 1\" deve estar visível na página inicial",
            "match": {
              "location": "src\\specs\\login.spec.js:54"
            },
            "result": {
              "status": "passed",
              "duration": 176000000
            }
          },
          {
            "arguments": [],
            "keyword": "E ",
            "line": 30,
            "name": "eu faço Logoff",
            "match": {
              "location": "src\\specs\\login.spec.js:58"
            },
            "result": {
              "status": "passed",
              "duration": 462000000
            }
          },
          {
            "arguments": [],
            "keyword": "E ",
            "line": 31,
            "name": "paro a gravação do BlazeMeter",
            "match": {
              "location": "src\\specs\\login.spec.js:69"
            },
            "result": {
              "status": "passed",
              "duration": 12050000000
            }
          },
          {
            "keyword": "After",
            "hidden": true,
            "match": {
              "location": "node_modules\\protractor-cucumber-framework\\lib\\resultsCapturer.js:27"
            },
            "result": {
              "status": "passed",
              "duration": 2000000
            }
          }
        ]
      }
    ]
  }
]